ntlmrecon/__init__.py
ntlmrecon/inpututils.py
ntlmrecon/misc.py
ntlmrecon/ntlmutil.py
ntlmrecon-0.2.1b0.dist-info/LICENSE
ntlmrecon-0.2.1b0.dist-info/METADATA
ntlmrecon-0.2.1b0.dist-info/WHEEL
ntlmrecon-0.2.1b0.dist-info/entry_points.txt
ntlmrecon-0.2.1b0.dist-info/top_level.txt
ntlmrecon-0.2.1b0.dist-info/RECORD
