Metadata-Version: 2.1
Name: ntlmrecon
Version: 0.2.1b0
Summary: A tool to enumerate information from NTLM authentication enabled web endpoints
Home-page: https://github.com/sachinkamath/ntlmrecon
Author: Sachin S Kamath (@sachinkamath)
Author-email: mail@skamath.me
License: UNKNOWN
Project-URL: Bug Reports, https://github.com/sachinkamath/ntlmrecon/issues
Project-URL: Source, https://github.com/sachinkamath/ntlmrecon/
Keywords: security recon redteam cybersecurity ntlm ntlmrecon
Platform: UNKNOWN
Requires-Python: >=2.7, !=3.0.*, !=3.1.*, !=3.2.*, !=3.3.*, !=3.4.*, <4
Requires-Dist: requests
Requires-Dist: colorama
Requires-Dist: termcolor
Requires-Dist: iptools
